[
  {
    "id": "CdeG4by6YE826o0RegX1",
    "picture": "images/nft/CdeG4by6YE826o0RegX1.png",
    "title": "Replicator",
    "author": "Mas Dog Jones",
    "description": "Lorem ipsum bla bla bla...",
    "price": 4114000,
    "comments": [
      {
        "date": "2021-09-21T01:03:25.010Z",
        "username": "Leanne Graham",
        "message": "est natus enim nihil est dolore omnis voluptatem numquam\net omnis occaecati quod ullam at\nvoluptatem error expedita pariatur\nnihil sint nostrum voluptatem reiciendis et"
      },
      {
        "date": "2020-09-11T01:01:45.010Z",
        "username": "Ervin Howell",
        "message": "non et atque\noccaecati deserunt quas accusantium unde odit nobis qui voluptatem\nquia voluptas consequuntur itaque dolor\net qui rerum deleniti ut occaecati"
      },
      {
        "date": "2021-09-10T01:02:45.010Z",
        "username": "Patricia Lebsack",
        "message": "doloribus at sed quis culpa deserunt consectetur qui praesentium\naccusamus fugiat dicta\nvoluptatem rerum ut voluptate autem\nvoluptatem repellendus aspernatur dolorem in"
      },
      {
        "date": "2020-04-11T01:02:45.010Z",
        "username": "Chelsey Dietrich",
        "message": "sapiente assumenda molestiae atque\nadipisci laborum distinctio aperiam et ab ut omnis\net occaecati aspernatur odit sit rem expedita\nquas enim ipsam minus"
      },
      {
        "date": "2020-05-12T01:02:45.010Z",
        "username": "Mrs. Dennis Schulist",
        "message": "voluptate iusto quis nobis reprehenderit ipsum amet nulla\nquia quas dolores velit et non\naut quia necessitatibus\nnostrum quaerat nulla et accusamus nisi facilis"
      }
    ],
    "category": [
      "most-valuable",
      "strange"
    ],
    "isAvaliable": true
  },
  {
    "id": "RmJ5Di91zS04t21LmuuW",
    "picture": "images/nft/RmJ5Di91zS04t21LmuuW.png",
    "title": "Everydays - The First 5000 Days",
    "author": "Beeple",
    "description": "Lorem ipsum bla bla bla...",
    "price": 69346250,
    "comments": [
      {
        "date": "2020-11-01T01:03:25.010Z",
        "username": "Glenna Reichert",
        "message": "sapiente assumenda molestiae atque\nadipisci laborum distinctio aperiam et ab ut omnis\net occaecati aspernatur odit sit rem expedita\nquas enim ipsam minus"
      },
      {
        "date": "2021-04-16T01:01:45.010Z",
        "username": "Clementina Dubuque",
        "message": "non et atque\noccaecati deserunt quas accusantium unde odit ni rerum deleniti ut occaecati"
      },
      {
        "date": "2020-02-11T01:02:45.010Z",
        "username": "Nicholas Runolfsdottir V",
        "message": "tem rerum ut voluptate autem\nvoluptatem repellendus aspernatur dolorem in"
      },
      {
        "date": "2020-03-11T01:02:45.010Z",
        "username": "Kurtis Weissnat",
        "message": "ut dolorum nostrum id quia aut est\nfuga est inventore vel eligendi explicabo quis consectetur\naut occaecati repellat id natus quo est\nut blanditiis quia ut vel ut maiores ea"
      }
    ],
    "category": [
      "most-valuable",
      "colorful"
    ],
    "isAvaliable": true
  },
  {
    "id": "9EfJ41XbxZ8U5Yfry0lI",
    "picture": "images/nft/9EfJ41XbxZ8U5Yfry0lI.png",
    "title": "CROSSROAD",
    "author": "Beeple",
    "description": "Lorem ipsum bla bla bla...",
    "price": 6666660,
    "comments": [
    {
      "date": "2020-01-01T01:03:25.010Z",
      "username": "Weissnat Reichert",
      "message": "et ab ut omnis\net occaecati aspernatur odit sit rem expedita\nquas enim ipsam minus"
    },
    {
      "date": "2021-07-21T01:01:45.010Z",
      "username": "Elvis Kurtis",
      "message": "nonfigurable multimedia task-forc"
    }
    ],
    "category": [
      "colorful",
      "strange"
    ],
    "isAvaliable": true
  },
  {
  "id": "i8tgeWfv32te5gf8GcvX",
  "picture": "images/nft/i8tgeWfv32te5gf8GcvX.jpg",
  "title": "Ocean Front",
  "author": "Beeple",
  "description": "Lorem ipsum bla bla bla...",
  "price": 6000000,
  "comments": [
    {
      "date": "2021-08-24T01:03:25.010Z",
      "username": "Kamren Graham",
      "message": "veritatis voluptates necessitatibus maiores corrupti\nneque et exercitationem amet sit et\nullam velit sit magnam laborum\nmagni ut molestias"
    },
    {
      "date": "2020-09-07T01:01:45.010Z",
      "username": "Dennis Howell",
      "message": "non itatibus maiores corrupti\nneque et exercitationem amet sit et\nullam velit sit magnam laborum consequuntur itaque dolor\net qui rerum deleniti ut occaecati"
    },
    {
      "date": "2019-11-04T01:02:45.010Z",
      "username": "Patricia Lebsack",
      "message": "tque\nadipisci laborum distinctio aperiam et ab ut omnis\netitationem amet sit et\nullam velit sit magnam laborum\nmas fugiat dicta\nvoluptatem rerum ut voluptate autem"
    },
    {
      "date": "2020-03-01T01:02:45.010Z",
      "username": "Lebsack Patricia",
      "message": "sapiente assumenda molestiae atque\nadipisci laborum distinctio aperiam et ab ut omnis\net occaecati aspernatur odit sit rem expedita\nquas enim ipsam minus"
    }
  ],
  "category": [
    "most-valuable",
    "colorful"
  ],
  "isAvaliable": true
  },
  {
    "id": "t5y7Id2bRT93CxZXuQaB",
    "picture": "images/nft/t5y7Id2bRT93CxZXuQaB.png",
    "title": "World Wide Web source code",
    "author": "Sir Tim Berners-Lee",
    "description": "Lorem ipsum bla bla bla...",
    "price": 5430000,
    "comments": [
      {
        "date": "2021-05-21T01:03:25.010Z",
        "username": "Christine Nathan",
        "message": "et\nfacere nihil ut voluptates in\nsaepe cupiditate accusantium numquam"
      },
      {
        "date": "2020-01-29T01:02:45.010Z",
        "username": "Preston Russel",
        "message": "aut culpa quaerat veritatis eos debitis\naut repellat eius explicabo et\nofficiis quo sint"
      }
    ],
    "category": [],
    "isAvaliable": true
  }
]